system_monitor/__init__.py
system_monitor/module.py
ykx_lab-0.2.0.dist-info/METADATA
ykx_lab-0.2.0.dist-info/WHEEL
ykx_lab-0.2.0.dist-info/top_level.txt
ykx_lab-0.2.0.dist-info/RECORD
