Metadata-Version: 2.1
Name: ykx-lab
Version: 0.2.0
Summary: personal tools for everyone.
Home-page: https://github.com/littlegump/ykx-lab
Author: RockyYin
Author-email: yinkaixuan0213@gmail.com
Classifier: Programming Language :: Python :: 3
Classifier: License :: OSI Approved :: MIT License
Classifier: Operating System :: OS Independent
Requires-Python: >=3.6
Requires-Dist: requests
Requires-Dist: flask
Requires-Dist: django
